opsduty_client/__init__.py
opsduty_client/api/__init__.py
opsduty_client/api/heartbeats/__init__.py
opsduty_client/api/heartbeats/opsduty_api_v1_heartbeats_create_heartbeat.py
opsduty_client/api/heartbeats/opsduty_api_v1_heartbeats_create_heartbeat_state.py
opsduty_client/api/heartbeats/opsduty_api_v1_heartbeats_delete_heartbeat.py
opsduty_client/api/heartbeats/opsduty_api_v1_heartbeats_delete_heartbeat_state.py
opsduty_client/api/heartbeats/opsduty_api_v1_heartbeats_healthcheck_environment_checkin.py
opsduty_client/api/heartbeats/opsduty_api_v1_heartbeats_list_heartbeats.py
opsduty_client/api/heartbeats/opsduty_api_v1_heartbeats_retrieve_heartbeat.py
opsduty_client/api/heartbeats/opsduty_api_v1_heartbeats_update_heartbeat.py
opsduty_client/api/heartbeats/opsduty_api_v1_heartbeats_update_heartbeat_state.py
opsduty_client/api/incidents/__init__.py
opsduty_client/api/incidents/opsduty_api_v1_incidents_list_incidents.py
opsduty_client/api/incidents/opsduty_api_v1_incidents_retrieve_incident.py
opsduty_client/api/incidents/opsduty_api_v1_incidents_retrieve_incident_reference.py
opsduty_client/api/schedules/__init__.py
opsduty_client/api/schedules/opsduty_api_v1_schedules_create_schedule_override.py
opsduty_client/api/schedules/opsduty_api_v1_schedules_delete_schedule_override.py
opsduty_client/api/schedules/opsduty_api_v1_schedules_list_schedule_overrides.py
opsduty_client/api/schedules/opsduty_api_v1_schedules_list_schedule_shifts.py
opsduty_client/api/schedules/opsduty_api_v1_schedules_list_services.py
opsduty_client/api/services/__init__.py
opsduty_client/api/services/opsduty_api_v1_services_list_service_oncall.py
opsduty_client/api/services/opsduty_api_v1_services_list_services.py
opsduty_client/api/users/__init__.py
opsduty_client/api/users/opsduty_api_v1_users_list_users.py
opsduty_client/client.py
opsduty_client/errors.py
opsduty_client/models/__init__.py
opsduty_client/models/create_heartbeat_input.py
opsduty_client/models/create_heartbeat_state_input.py
opsduty_client-0.0.7.dist-info/METADATA
opsduty_client-0.0.7.dist-info/WHEEL
opsduty_client-0.0.7.dist-info/RECORD
